[
  {
    "color": "#FF0000",
    "author": "Martin Luther King Jr.",
    "quote": "If you can't fly then run, if you can't run then walk, if you can't walk then crawl, but whatever you do, you have to keep moving forward."
  },
  {
    "color": "#808080",
    "author": "Christopher Reeve",
    "quote": "A hero is an ordinary individual who finds the strength to persevere and endure in spite of overwhelming obstacles."
  },
  {
    "color": "#FFFF00",
    "author": "Oprah Winfrey ",
    "quote": "Where there is no struggle, there is no strength."
  },
  {
    "color": "#800000",
    "author": "Deepak Chopra",
    "quote": "The past is gone, the future is not here, now I am free of both. Right now, I choose joy."
  },
  {
    "color": "#808000",
    "author": "Winston Churchill",
    "quote": "Success is not final, failure is not fatal: it is the courage to continue that counts."
  },
  {
    "color": "#008000",
    "author": "Zig Ziglar ",
    "quote": "What you get by achieving your goals is not as important as what you become by achieving your goals."
  },
  {
    "color": "#00FFFF",
    "author": "Albert Einstein ",
    "quote": "Life is like riding a bicycle. To keep your balance, you must keep moving."
  },
  {
    "color": "#008080",
    "author": "Mahatma Gandhi",
    "quote": "Action expresses priorities"
  },
  {
    "color": "#0000FF",
    "author": "Jawaharlal Nehru",
    "quote": "Life is like a game of cards. The hand you are dealt is determinism; the way you play it is free will."
  },
  {
    "color": "#800080",
    "author": "Rabindranath Tagore",
    "quote": "Don’t limit a child to your own learning, for he was born in another time."
  }
]